ipdf/__init__.py
ipdf/game.py
ipdf/helper.py
ipdf/strategies/__init__.py
ipdf/strategies/abstract.py
ipdf/strategies/memory_based.py
ipdframework-0.1.dist-info/LICENSE
ipdframework-0.1.dist-info/METADATA
ipdframework-0.1.dist-info/WHEEL
ipdframework-0.1.dist-info/top_level.txt
ipdframework-0.1.dist-info/RECORD
