Metadata-Version: 2.1
Name: ipdframework
Version: 0.1
Summary: Library for the iterated evolutionary tournaments between memory-based agents
Home-page: https://github.com/dmitry-tk/ipdf
Author: Dmytro Tkachyk
Author-email: dmitry.tkk@gmail.com
License: UNKNOWN
Keywords: game-theory,strategy
Platform: UNKNOWN
Classifier: Intended Audience :: Developers
Classifier: Natural Language :: English
Classifier: Programming Language :: Python :: 3.6
Requires-Python: >=3.6,<4
Requires-Dist: colorful (==0.5.4)
Requires-Dist: numpy (==1.18.1)
Provides-Extra: dev
Requires-Dist: pytest (==5.2.1) ; extra == 'dev'
Requires-Dist: twine (==1.12.1) ; extra == 'dev'
Requires-Dist: wheel (==0.33.6) ; extra == 'dev'
Provides-Extra: linter
Requires-Dist: flake8 (==3.7.8) ; extra == 'linter'
